{
  "documentId": "sdk-bun-integration",
  "title": "sdk-bun-integration",
  "tree": {
    "title": "sdk-bun-integration",
    "node_id": "000",
    "start_index": 0,
    "end_index": 20,
    "summary": "Documentation for sdk-bun-integration",
    "level": 0,
    "nodes": [
      {
        "title": "Bun Integration",
        "node_id": "000",
        "start_index": 0,
        "end_index": 1,
        "summary": "Section about Bun Integration",
        "level": 1,
        "nodes": []
      },
      {
        "title": "Architecture",
        "node_id": "001",
        "start_index": 1,
        "end_index": 2,
        "summary": "Section about Architecture",
        "level": 1,
        "nodes": []
      },
      {
        "title": "SQLite Store",
        "node_id": "002",
        "start_index": 2,
        "end_index": 3,
        "summary": "Section about SQLite Store",
        "level": 1,
        "nodes": []
      },
      {
        "title": "Setup",
        "node_id": "003",
        "start_index": 3,
        "end_index": 4,
        "summary": "Section about Setup",
        "level": 1,
        "nodes": []
      },
      {
        "title": "Operations",
        "node_id": "004",
        "start_index": 4,
        "end_index": 5,
        "summary": "Section about Operations",
        "level": 1,
        "nodes": []
      },
      {
        "title": "Event Listening",
        "node_id": "005",
        "start_index": 5,
        "end_index": 6,
        "summary": "Section about Event Listening",
        "level": 1,
        "nodes": []
      },
      {
        "title": "Use with RecordKeeper",
        "node_id": "006",
        "start_index": 6,
        "end_index": 7,
        "summary": "Section about Use with RecordKeeper",
        "level": 1,
        "nodes": []
      },
      {
        "title": "Bun Server",
        "node_id": "007",
        "start_index": 7,
        "end_index": 8,
        "summary": "Section about Bun Server",
        "level": 1,
        "nodes": []
      },
      {
        "title": "Basic Server",
        "node_id": "008",
        "start_index": 8,
        "end_index": 9,
        "summary": "Section about Basic Server",
        "level": 1,
        "nodes": []
      },
      {
        "title": "Server with SDK Integration",
        "node_id": "009",
        "start_index": 9,
        "end_index": 10,
        "summary": "Section about Server with SDK Integration",
        "level": 1,
        "nodes": []
      },
      {
        "title": "WebSocket Server",
        "node_id": "010",
        "start_index": 10,
        "end_index": 11,
        "summary": "Section about WebSocket Server",
        "level": 1,
        "nodes": []
      },
      {
        "title": "Performance Benefits",
        "node_id": "011",
        "start_index": 11,
        "end_index": 12,
        "summary": "Section about Performance Benefits",
        "level": 1,
        "nodes": []
      },
      {
        "title": "SQLite vs File System",
        "node_id": "012",
        "start_index": 12,
        "end_index": 13,
        "summary": "Section about SQLite vs File System",
        "level": 1,
        "nodes": []
      },
      {
        "title": "Benchmarks",
        "node_id": "013",
        "start_index": 13,
        "end_index": 14,
        "summary": "Section about Benchmarks",
        "level": 1,
        "nodes": []
      },
      {
        "title": "Complete Example",
        "node_id": "014",
        "start_index": 14,
        "end_index": 15,
        "summary": "Section about Complete Example",
        "level": 1,
        "nodes": []
      },
      {
        "title": "Configuration",
        "node_id": "015",
        "start_index": 15,
        "end_index": 16,
        "summary": "Section about Configuration",
        "level": 1,
        "nodes": []
      },
      {
        "title": "SQLite Options",
        "node_id": "016",
        "start_index": 16,
        "end_index": 17,
        "summary": "Section about SQLite Options",
        "level": 1,
        "nodes": []
      },
      {
        "title": "Server Options",
        "node_id": "017",
        "start_index": 17,
        "end_index": 18,
        "summary": "Section about Server Options",
        "level": 1,
        "nodes": []
      },
      {
        "title": "Related",
        "node_id": "018",
        "start_index": 18,
        "end_index": 19,
        "summary": "Section about Related",
        "level": 1,
        "nodes": []
      },
      {
        "title": "Links",
        "node_id": "019",
        "start_index": 19,
        "end_index": 20,
        "summary": "Section about Links",
        "level": 1,
        "nodes": []
      }
    ]
  },
  "sections": [
    {
      "title": "sdk-bun-integration",
      "node_id": "000",
      "start_index": 0,
      "end_index": 20,
      "summary": "Documentation for sdk-bun-integration",
      "level": 0,
      "nodes": [
        {
          "title": "Bun Integration",
          "node_id": "000",
          "start_index": 0,
          "end_index": 1,
          "summary": "Section about Bun Integration",
          "level": 1,
          "nodes": []
        },
        {
          "title": "Architecture",
          "node_id": "001",
          "start_index": 1,
          "end_index": 2,
          "summary": "Section about Architecture",
          "level": 1,
          "nodes": []
        },
        {
          "title": "SQLite Store",
          "node_id": "002",
          "start_index": 2,
          "end_index": 3,
          "summary": "Section about SQLite Store",
          "level": 1,
          "nodes": []
        },
        {
          "title": "Setup",
          "node_id": "003",
          "start_index": 3,
          "end_index": 4,
          "summary": "Section about Setup",
          "level": 1,
          "nodes": []
        },
        {
          "title": "Operations",
          "node_id": "004",
          "start_index": 4,
          "end_index": 5,
          "summary": "Section about Operations",
          "level": 1,
          "nodes": []
        },
        {
          "title": "Event Listening",
          "node_id": "005",
          "start_index": 5,
          "end_index": 6,
          "summary": "Section about Event Listening",
          "level": 1,
          "nodes": []
        },
        {
          "title": "Use with RecordKeeper",
          "node_id": "006",
          "start_index": 6,
          "end_index": 7,
          "summary": "Section about Use with RecordKeeper",
          "level": 1,
          "nodes": []
        },
        {
          "title": "Bun Server",
          "node_id": "007",
          "start_index": 7,
          "end_index": 8,
          "summary": "Section about Bun Server",
          "level": 1,
          "nodes": []
        },
        {
          "title": "Basic Server",
          "node_id": "008",
          "start_index": 8,
          "end_index": 9,
          "summary": "Section about Basic Server",
          "level": 1,
          "nodes": []
        },
        {
          "title": "Server with SDK Integration",
          "node_id": "009",
          "start_index": 9,
          "end_index": 10,
          "summary": "Section about Server with SDK Integration",
          "level": 1,
          "nodes": []
        },
        {
          "title": "WebSocket Server",
          "node_id": "010",
          "start_index": 10,
          "end_index": 11,
          "summary": "Section about WebSocket Server",
          "level": 1,
          "nodes": []
        },
        {
          "title": "Performance Benefits",
          "node_id": "011",
          "start_index": 11,
          "end_index": 12,
          "summary": "Section about Performance Benefits",
          "level": 1,
          "nodes": []
        },
        {
          "title": "SQLite vs File System",
          "node_id": "012",
          "start_index": 12,
          "end_index": 13,
          "summary": "Section about SQLite vs File System",
          "level": 1,
          "nodes": []
        },
        {
          "title": "Benchmarks",
          "node_id": "013",
          "start_index": 13,
          "end_index": 14,
          "summary": "Section about Benchmarks",
          "level": 1,
          "nodes": []
        },
        {
          "title": "Complete Example",
          "node_id": "014",
          "start_index": 14,
          "end_index": 15,
          "summary": "Section about Complete Example",
          "level": 1,
          "nodes": []
        },
        {
          "title": "Configuration",
          "node_id": "015",
          "start_index": 15,
          "end_index": 16,
          "summary": "Section about Configuration",
          "level": 1,
          "nodes": []
        },
        {
          "title": "SQLite Options",
          "node_id": "016",
          "start_index": 16,
          "end_index": 17,
          "summary": "Section about SQLite Options",
          "level": 1,
          "nodes": []
        },
        {
          "title": "Server Options",
          "node_id": "017",
          "start_index": 17,
          "end_index": 18,
          "summary": "Section about Server Options",
          "level": 1,
          "nodes": []
        },
        {
          "title": "Related",
          "node_id": "018",
          "start_index": 18,
          "end_index": 19,
          "summary": "Section about Related",
          "level": 1,
          "nodes": []
        },
        {
          "title": "Links",
          "node_id": "019",
          "start_index": 19,
          "end_index": 20,
          "summary": "Section about Links",
          "level": 1,
          "nodes": []
        }
      ]
    },
    {
      "title": "Bun Integration",
      "node_id": "000",
      "start_index": 0,
      "end_index": 1,
      "summary": "Section about Bun Integration",
      "level": 1,
      "nodes": []
    },
    {
      "title": "Architecture",
      "node_id": "001",
      "start_index": 1,
      "end_index": 2,
      "summary": "Section about Architecture",
      "level": 1,
      "nodes": []
    },
    {
      "title": "SQLite Store",
      "node_id": "002",
      "start_index": 2,
      "end_index": 3,
      "summary": "Section about SQLite Store",
      "level": 1,
      "nodes": []
    },
    {
      "title": "Setup",
      "node_id": "003",
      "start_index": 3,
      "end_index": 4,
      "summary": "Section about Setup",
      "level": 1,
      "nodes": []
    },
    {
      "title": "Operations",
      "node_id": "004",
      "start_index": 4,
      "end_index": 5,
      "summary": "Section about Operations",
      "level": 1,
      "nodes": []
    },
    {
      "title": "Event Listening",
      "node_id": "005",
      "start_index": 5,
      "end_index": 6,
      "summary": "Section about Event Listening",
      "level": 1,
      "nodes": []
    },
    {
      "title": "Use with RecordKeeper",
      "node_id": "006",
      "start_index": 6,
      "end_index": 7,
      "summary": "Section about Use with RecordKeeper",
      "level": 1,
      "nodes": []
    },
    {
      "title": "Bun Server",
      "node_id": "007",
      "start_index": 7,
      "end_index": 8,
      "summary": "Section about Bun Server",
      "level": 1,
      "nodes": []
    },
    {
      "title": "Basic Server",
      "node_id": "008",
      "start_index": 8,
      "end_index": 9,
      "summary": "Section about Basic Server",
      "level": 1,
      "nodes": []
    },
    {
      "title": "Server with SDK Integration",
      "node_id": "009",
      "start_index": 9,
      "end_index": 10,
      "summary": "Section about Server with SDK Integration",
      "level": 1,
      "nodes": []
    },
    {
      "title": "WebSocket Server",
      "node_id": "010",
      "start_index": 10,
      "end_index": 11,
      "summary": "Section about WebSocket Server",
      "level": 1,
      "nodes": []
    },
    {
      "title": "Performance Benefits",
      "node_id": "011",
      "start_index": 11,
      "end_index": 12,
      "summary": "Section about Performance Benefits",
      "level": 1,
      "nodes": []
    },
    {
      "title": "SQLite vs File System",
      "node_id": "012",
      "start_index": 12,
      "end_index": 13,
      "summary": "Section about SQLite vs File System",
      "level": 1,
      "nodes": []
    },
    {
      "title": "Benchmarks",
      "node_id": "013",
      "start_index": 13,
      "end_index": 14,
      "summary": "Section about Benchmarks",
      "level": 1,
      "nodes": []
    },
    {
      "title": "Complete Example",
      "node_id": "014",
      "start_index": 14,
      "end_index": 15,
      "summary": "Section about Complete Example",
      "level": 1,
      "nodes": []
    },
    {
      "title": "Configuration",
      "node_id": "015",
      "start_index": 15,
      "end_index": 16,
      "summary": "Section about Configuration",
      "level": 1,
      "nodes": []
    },
    {
      "title": "SQLite Options",
      "node_id": "016",
      "start_index": 16,
      "end_index": 17,
      "summary": "Section about SQLite Options",
      "level": 1,
      "nodes": []
    },
    {
      "title": "Server Options",
      "node_id": "017",
      "start_index": 17,
      "end_index": 18,
      "summary": "Section about Server Options",
      "level": 1,
      "nodes": []
    },
    {
      "title": "Related",
      "node_id": "018",
      "start_index": 18,
      "end_index": 19,
      "summary": "Section about Related",
      "level": 1,
      "nodes": []
    },
    {
      "title": "Links",
      "node_id": "019",
      "start_index": 19,
      "end_index": 20,
      "summary": "Section about Links",
      "level": 1,
      "nodes": []
    }
  ],
  "indexedAt": "2026-02-27T18:54:08.899Z"
}